demo/handler_demo.py
flumen/__init__.py
flumen/event_base.py
flumen/mixins.py
flumen-0.1.dist-info/METADATA
flumen-0.1.dist-info/RECORD
flumen-0.1.dist-info/WHEEL
flumen-0.1.dist-info/top_level.txt
