Metadata-Version: 2.1
Name: flumen
Version: 0.1
Summary: Event stream framework
Home-page: https://github.com/pangyun/flumen
Author: Xu Peng
Author-email: xupeng3112@163.com
License: UNKNOWN
Platform: UNKNOWN
